{
  "features_B_classifier": [
    "Tr_ProbSS",
    "Tr_diff_z",
    "Tr_p_proj",
    "Tr_diff_pt",
    "Tr_diff_p",
    "Tr_cos_diff_phi",
    "Tr_diff_eta",
    "Tr_T_IPCHI2_trMother",
    "Tr_T_IP_trMother",
    "Tr_T_IP_trPUS",
    "Tr_T_MinIP",
    "Tr_T_MinIPChi2",
    "Tr_T_PROBNNe",
    "Tr_T_PROBNNghost",
    "Tr_T_PROBNNk",
    "Tr_T_PROBNNmu",
    "Tr_T_PROBNNp",
    "Tr_T_PROBNNpi",
    "Tr_T_P",
    "Tr_T_PT",
    "Tr_T_VeloCharge",
    "Tr_T_ACHI2DOCA",
    "Tr_T_ADOCA",
    "Tr_T_SumBDT_ult",
    "Tr_T_MinBDT_ult"
  ],
  "features_B_classifier_without_Tr_ProbSS": [
    "Tr_diff_z",
    "Tr_p_proj",
    "Tr_diff_pt",
    "Tr_diff_p",
    "Tr_cos_diff_phi",
    "Tr_diff_eta",
    "Tr_T_IPCHI2_trMother",
    "Tr_T_IP_trMother",
    "Tr_T_IP_trPUS",
    "Tr_T_MinIP",
    "Tr_T_MinIPChi2",
    "Tr_T_PROBNNe",
    "Tr_T_PROBNNghost",
    "Tr_T_PROBNNk",
    "Tr_T_PROBNNmu",
    "Tr_T_PROBNNp",
    "Tr_T_PROBNNpi",
    "Tr_T_P",
    "Tr_T_PT",
    "Tr_T_VeloCharge",
    "Tr_T_ACHI2DOCA",
    "Tr_T_ADOCA",
    "Tr_T_SumBDT_ult",
    "Tr_T_MinBDT_ult"
  ],
  "features_B_classifier_minimal": [
    "Tr_ProbSS",
    "Tr_T_PROBNNe",
    "Tr_T_PROBNNghost",
    "Tr_T_PROBNNk",
    "Tr_T_PROBNNmu",
    "Tr_T_PROBNNp",
    "Tr_T_PROBNNpi"
  ],
  "features_B_classifier_baseline": [
    "Tr_ProbSS",
    "Tr_diff_z",
    "Tr_p_proj",
    "Tr_diff_pt",
    "Tr_diff_p",
    "Tr_cos_diff_phi",
    "Tr_diff_eta",
    "Tr_T_IPCHI2_trMother",
    "Tr_T_IP_trMother",
    "Tr_T_IP_trPUS",
    "Tr_T_MinIP",
    "Tr_T_MinIPChi2",
    "Tr_T_PROBNNe",
    "Tr_T_PROBNNghost",
    "Tr_T_PROBNNk",
    "Tr_T_PROBNNmu",
    "Tr_T_PROBNNp",
    "Tr_T_PROBNNpi",
    "Tr_T_P",
    "Tr_T_PT",
    "Tr_T_VeloCharge"
  ],
  "features_B_classifier_baseline_with_Tr_is_SS": [
    "Tr_ProbSS",
    "Tr_is_SS",
    "Tr_diff_z",
    "Tr_p_proj",
    "Tr_diff_pt",
    "Tr_diff_p",
    "Tr_cos_diff_phi",
    "Tr_diff_eta",
    "Tr_T_IPCHI2_trMother",
    "Tr_T_IP_trMother",
    "Tr_T_IP_trPUS",
    "Tr_T_MinIP",
    "Tr_T_MinIPChi2",
    "Tr_T_PROBNNe",
    "Tr_T_PROBNNghost",
    "Tr_T_PROBNNk",
    "Tr_T_PROBNNmu",
    "Tr_T_PROBNNp",
    "Tr_T_PROBNNpi",
    "Tr_T_P",
    "Tr_T_PT",
    "Tr_T_VeloCharge"
  ],
  "features_B_classifier_baseline_with_Tr_T_Best_PAIR_M_fromiso": [
    "Tr_ProbSS",
    "Tr_diff_z",
    "Tr_p_proj",
    "Tr_diff_pt",
    "Tr_diff_p",
    "Tr_cos_diff_phi",
    "Tr_diff_eta",
    "Tr_T_IPCHI2_trMother",
    "Tr_T_IP_trMother",
    "Tr_T_IP_trPUS",
    "Tr_T_MinIP",
    "Tr_T_MinIPChi2",
    "Tr_T_PROBNNe",
    "Tr_T_PROBNNghost",
    "Tr_T_PROBNNk",
    "Tr_T_PROBNNmu",
    "Tr_T_PROBNNp",
    "Tr_T_PROBNNpi",
    "Tr_T_P",
    "Tr_T_PT",
    "Tr_T_VeloCharge",
    "Tr_T_Best_PAIR_M_fromiso"
  ],
  "features_B_classifier_baseline_with_Tr_T_Ntr_incone": [
    "Tr_ProbSS",
    "Tr_diff_z",
    "Tr_p_proj",
    "Tr_diff_pt",
    "Tr_diff_p",
    "Tr_cos_diff_phi",
    "Tr_diff_eta",
    "Tr_T_IPCHI2_trMother",
    "Tr_T_IP_trMother",
    "Tr_T_IP_trPUS",
    "Tr_T_MinIP",
    "Tr_T_MinIPChi2",
    "Tr_T_PROBNNe",
    "Tr_T_PROBNNghost",
    "Tr_T_PROBNNk",
    "Tr_T_PROBNNmu",
    "Tr_T_PROBNNp",
    "Tr_T_PROBNNpi",
    "Tr_T_P",
    "Tr_T_PT",
    "Tr_T_VeloCharge",
    "Tr_T_Ntr_incone"
  ],
  "features_B_classifier_baseline_with_Tr_T_Charge": [
    "Tr_ProbSS",
    "Tr_diff_z",
    "Tr_p_proj",
    "Tr_diff_pt",
    "Tr_diff_p",
    "Tr_cos_diff_phi",
    "Tr_diff_eta",
    "Tr_T_IPCHI2_trMother",
    "Tr_T_IP_trMother",
    "Tr_T_IP_trPUS",
    "Tr_T_MinIP",
    "Tr_T_MinIPChi2",
    "Tr_T_PROBNNe",
    "Tr_T_PROBNNghost",
    "Tr_T_PROBNNk",
    "Tr_T_PROBNNmu",
    "Tr_T_PROBNNp",
    "Tr_T_PROBNNpi",
    "Tr_T_P",
    "Tr_T_PT",
    "Tr_T_VeloCharge",
    "Tr_T_Charge"
  ],
  "features_B_classifier_baseline_with_Tr_T_TRPCHI2": [
    "Tr_ProbSS",
    "Tr_diff_z",
    "Tr_p_proj",
    "Tr_diff_pt",
    "Tr_diff_p",
    "Tr_cos_diff_phi",
    "Tr_diff_eta",
    "Tr_T_IPCHI2_trMother",
    "Tr_T_IP_trMother",
    "Tr_T_IP_trPUS",
    "Tr_T_MinIP",
    "Tr_T_MinIPChi2",
    "Tr_T_PROBNNe",
    "Tr_T_PROBNNghost",
    "Tr_T_PROBNNk",
    "Tr_T_PROBNNmu",
    "Tr_T_PROBNNp",
    "Tr_T_PROBNNpi",
    "Tr_T_P",
    "Tr_T_PT",
    "Tr_T_VeloCharge",
    "Tr_T_TRPCHI2"
  ],
  "features_B_classifier_baseline_with_Tr_T_SumMinBDT_ult": [
    "Tr_ProbSS",
    "Tr_diff_z",
    "Tr_p_proj",
    "Tr_diff_pt",
    "Tr_diff_p",
    "Tr_cos_diff_phi",
    "Tr_diff_eta",
    "Tr_T_IPCHI2_trMother",
    "Tr_T_IP_trMother",
    "Tr_T_IP_trPUS",
    "Tr_T_MinIP",
    "Tr_T_MinIPChi2",
    "Tr_T_PROBNNe",
    "Tr_T_PROBNNghost",
    "Tr_T_PROBNNk",
    "Tr_T_PROBNNmu",
    "Tr_T_PROBNNp",
    "Tr_T_PROBNNpi",
    "Tr_T_P",
    "Tr_T_PT",
    "Tr_T_VeloCharge",
    "Tr_T_SumMinBDT_ult"
  ],
  "features_B_classifier_baseline_with_Tr_T_MinBDT_sigtr": [
    "Tr_ProbSS",
    "Tr_diff_z",
    "Tr_p_proj",
    "Tr_diff_pt",
    "Tr_diff_p",
    "Tr_cos_diff_phi",
    "Tr_diff_eta",
    "Tr_T_IPCHI2_trMother",
    "Tr_T_IP_trMother",
    "Tr_T_IP_trPUS",
    "Tr_T_MinIP",
    "Tr_T_MinIPChi2",
    "Tr_T_PROBNNe",
    "Tr_T_PROBNNghost",
    "Tr_T_PROBNNk",
    "Tr_T_PROBNNmu",
    "Tr_T_PROBNNp",
    "Tr_T_PROBNNpi",
    "Tr_T_P",
    "Tr_T_PT",
    "Tr_T_VeloCharge",
    "Tr_T_MinBDT_sigtr"
  ],
  "features_B_classifier_baseline_with_Tr_T_ACHI2DOCA": [
    "Tr_ProbSS",
    "Tr_diff_z",
    "Tr_p_proj",
    "Tr_diff_pt",
    "Tr_diff_p",
    "Tr_cos_diff_phi",
    "Tr_diff_eta",
    "Tr_T_IPCHI2_trMother",
    "Tr_T_IP_trMother",
    "Tr_T_IP_trPUS",
    "Tr_T_MinIP",
    "Tr_T_MinIPChi2",
    "Tr_T_PROBNNe",
    "Tr_T_PROBNNghost",
    "Tr_T_PROBNNk",
    "Tr_T_PROBNNmu",
    "Tr_T_PROBNNp",
    "Tr_T_PROBNNpi",
    "Tr_T_P",
    "Tr_T_PT",
    "Tr_T_VeloCharge",
    "Tr_T_ACHI2DOCA"
  ],
  "features_B_classifier_baseline_with_Tr_T_TRFITTCHI2": [
    "Tr_ProbSS",
    "Tr_diff_z",
    "Tr_p_proj",
    "Tr_diff_pt",
    "Tr_diff_p",
    "Tr_cos_diff_phi",
    "Tr_diff_eta",
    "Tr_T_IPCHI2_trMother",
    "Tr_T_IP_trMother",
    "Tr_T_IP_trPUS",
    "Tr_T_MinIP",
    "Tr_T_MinIPChi2",
    "Tr_T_PROBNNe",
    "Tr_T_PROBNNghost",
    "Tr_T_PROBNNk",
    "Tr_T_PROBNNmu",
    "Tr_T_PROBNNp",
    "Tr_T_PROBNNpi",
    "Tr_T_P",
    "Tr_T_PT",
    "Tr_T_VeloCharge",
    "Tr_T_TRFITTCHI2"
  ],
  "features_B_classifier_baseline_with_Tr_T_NbNonIsoTr_ult": [
    "Tr_ProbSS",
    "Tr_diff_z",
    "Tr_p_proj",
    "Tr_diff_pt",
    "Tr_diff_p",
    "Tr_cos_diff_phi",
    "Tr_diff_eta",
    "Tr_T_IPCHI2_trMother",
    "Tr_T_IP_trMother",
    "Tr_T_IP_trPUS",
    "Tr_T_MinIP",
    "Tr_T_MinIPChi2",
    "Tr_T_PROBNNe",
    "Tr_T_PROBNNghost",
    "Tr_T_PROBNNk",
    "Tr_T_PROBNNmu",
    "Tr_T_PROBNNp",
    "Tr_T_PROBNNpi",
    "Tr_T_P",
    "Tr_T_PT",
    "Tr_T_VeloCharge",
    "Tr_T_NbNonIsoTr_ult"
  ],
  "features_B_classifier_baseline_with_Tr_T_SumBDT_sigtr": [
    "Tr_ProbSS",
    "Tr_diff_z",
    "Tr_p_proj",
    "Tr_diff_pt",
    "Tr_diff_p",
    "Tr_cos_diff_phi",
    "Tr_diff_eta",
    "Tr_T_IPCHI2_trMother",
    "Tr_T_IP_trMother",
    "Tr_T_IP_trPUS",
    "Tr_T_MinIP",
    "Tr_T_MinIPChi2",
    "Tr_T_PROBNNe",
    "Tr_T_PROBNNghost",
    "Tr_T_PROBNNk",
    "Tr_T_PROBNNmu",
    "Tr_T_PROBNNp",
    "Tr_T_PROBNNpi",
    "Tr_T_P",
    "Tr_T_PT",
    "Tr_T_VeloCharge",
    "Tr_T_SumBDT_sigtr"
  ],
  "features_B_classifier_baseline_with_Tr_T_TRCHI2DOF": [
    "Tr_ProbSS",
    "Tr_diff_z",
    "Tr_p_proj",
    "Tr_diff_pt",
    "Tr_diff_p",
    "Tr_cos_diff_phi",
    "Tr_diff_eta",
    "Tr_T_IPCHI2_trMother",
    "Tr_T_IP_trMother",
    "Tr_T_IP_trPUS",
    "Tr_T_MinIP",
    "Tr_T_MinIPChi2",
    "Tr_T_PROBNNe",
    "Tr_T_PROBNNghost",
    "Tr_T_PROBNNk",
    "Tr_T_PROBNNmu",
    "Tr_T_PROBNNp",
    "Tr_T_PROBNNpi",
    "Tr_T_P",
    "Tr_T_PT",
    "Tr_T_VeloCharge",
    "Tr_T_TRCHI2DOF"
  ],
  "features_B_classifier_baseline_with_Tr_T_TrFITTCHI2NDOF": [
    "Tr_ProbSS",
    "Tr_diff_z",
    "Tr_p_proj",
    "Tr_diff_pt",
    "Tr_diff_p",
    "Tr_cos_diff_phi",
    "Tr_diff_eta",
    "Tr_T_IPCHI2_trMother",
    "Tr_T_IP_trMother",
    "Tr_T_IP_trPUS",
    "Tr_T_MinIP",
    "Tr_T_MinIPChi2",
    "Tr_T_PROBNNe",
    "Tr_T_PROBNNghost",
    "Tr_T_PROBNNk",
    "Tr_T_PROBNNmu",
    "Tr_T_PROBNNp",
    "Tr_T_PROBNNpi",
    "Tr_T_P",
    "Tr_T_PT",
    "Tr_T_VeloCharge",
    "Tr_T_TrFITTCHI2NDOF"
  ],
  "features_B_classifier_baseline_with_Tr_T_AALLSAMEBPV": [
    "Tr_ProbSS",
    "Tr_diff_z",
    "Tr_p_proj",
    "Tr_diff_pt",
    "Tr_diff_p",
    "Tr_cos_diff_phi",
    "Tr_diff_eta",
    "Tr_T_IPCHI2_trMother",
    "Tr_T_IP_trMother",
    "Tr_T_IP_trPUS",
    "Tr_T_MinIP",
    "Tr_T_MinIPChi2",
    "Tr_T_PROBNNe",
    "Tr_T_PROBNNghost",
    "Tr_T_PROBNNk",
    "Tr_T_PROBNNmu",
    "Tr_T_PROBNNp",
    "Tr_T_PROBNNpi",
    "Tr_T_P",
    "Tr_T_PT",
    "Tr_T_VeloCharge",
    "Tr_T_AALLSAMEBPV"
  ],
  "features_B_classifier_baseline_with_Tr_T_ISMUON": [
    "Tr_ProbSS",
    "Tr_diff_z",
    "Tr_p_proj",
    "Tr_diff_pt",
    "Tr_diff_p",
    "Tr_cos_diff_phi",
    "Tr_diff_eta",
    "Tr_T_IPCHI2_trMother",
    "Tr_T_IP_trMother",
    "Tr_T_IP_trPUS",
    "Tr_T_MinIP",
    "Tr_T_MinIPChi2",
    "Tr_T_PROBNNe",
    "Tr_T_PROBNNghost",
    "Tr_T_PROBNNk",
    "Tr_T_PROBNNmu",
    "Tr_T_PROBNNp",
    "Tr_T_PROBNNpi",
    "Tr_T_P",
    "Tr_T_PT",
    "Tr_T_VeloCharge",
    "Tr_T_ISMUON"
  ],
  "features_B_classifier_baseline_with_Tr_T_ConIso_pt_ult": [
    "Tr_ProbSS",
    "Tr_diff_z",
    "Tr_p_proj",
    "Tr_diff_pt",
    "Tr_diff_p",
    "Tr_cos_diff_phi",
    "Tr_diff_eta",
    "Tr_T_IPCHI2_trMother",
    "Tr_T_IP_trMother",
    "Tr_T_IP_trPUS",
    "Tr_T_MinIP",
    "Tr_T_MinIPChi2",
    "Tr_T_PROBNNe",
    "Tr_T_PROBNNghost",
    "Tr_T_PROBNNk",
    "Tr_T_PROBNNmu",
    "Tr_T_PROBNNp",
    "Tr_T_PROBNNpi",
    "Tr_T_P",
    "Tr_T_PT",
    "Tr_T_VeloCharge",
    "Tr_T_ConIso_pt_ult"
  ],
  "features_B_classifier_baseline_with_Tr_T_TRFITVELOCHI2NDOF": [
    "Tr_ProbSS",
    "Tr_diff_z",
    "Tr_p_proj",
    "Tr_diff_pt",
    "Tr_diff_p",
    "Tr_cos_diff_phi",
    "Tr_diff_eta",
    "Tr_T_IPCHI2_trMother",
    "Tr_T_IP_trMother",
    "Tr_T_IP_trPUS",
    "Tr_T_MinIP",
    "Tr_T_MinIPChi2",
    "Tr_T_PROBNNe",
    "Tr_T_PROBNNghost",
    "Tr_T_PROBNNk",
    "Tr_T_PROBNNmu",
    "Tr_T_PROBNNp",
    "Tr_T_PROBNNpi",
    "Tr_T_P",
    "Tr_T_PT",
    "Tr_T_VeloCharge",
    "Tr_T_TRFITVELOCHI2NDOF"
  ],
  "features_B_classifier_baseline_with_Tr_T_PIDmu": [
    "Tr_ProbSS",
    "Tr_diff_z",
    "Tr_p_proj",
    "Tr_diff_pt",
    "Tr_diff_p",
    "Tr_cos_diff_phi",
    "Tr_diff_eta",
    "Tr_T_IPCHI2_trMother",
    "Tr_T_IP_trMother",
    "Tr_T_IP_trPUS",
    "Tr_T_MinIP",
    "Tr_T_MinIPChi2",
    "Tr_T_PROBNNe",
    "Tr_T_PROBNNghost",
    "Tr_T_PROBNNk",
    "Tr_T_PROBNNmu",
    "Tr_T_PROBNNp",
    "Tr_T_PROBNNpi",
    "Tr_T_P",
    "Tr_T_PT",
    "Tr_T_VeloCharge",
    "Tr_T_PIDmu"
  ],
  "features_B_classifier_baseline_with_Tr_T_x": [
    "Tr_ProbSS",
    "Tr_diff_z",
    "Tr_p_proj",
    "Tr_diff_pt",
    "Tr_diff_p",
    "Tr_cos_diff_phi",
    "Tr_diff_eta",
    "Tr_T_IPCHI2_trMother",
    "Tr_T_IP_trMother",
    "Tr_T_IP_trPUS",
    "Tr_T_MinIP",
    "Tr_T_MinIPChi2",
    "Tr_T_PROBNNe",
    "Tr_T_PROBNNghost",
    "Tr_T_PROBNNk",
    "Tr_T_PROBNNmu",
    "Tr_T_PROBNNp",
    "Tr_T_PROBNNpi",
    "Tr_T_P",
    "Tr_T_PT",
    "Tr_T_VeloCharge",
    "Tr_T_x"
  ],
  "features_B_classifier_baseline_with_Tr_T_SumBDT_ult": [
    "Tr_ProbSS",
    "Tr_diff_z",
    "Tr_p_proj",
    "Tr_diff_pt",
    "Tr_diff_p",
    "Tr_cos_diff_phi",
    "Tr_diff_eta",
    "Tr_T_IPCHI2_trMother",
    "Tr_T_IP_trMother",
    "Tr_T_IP_trPUS",
    "Tr_T_MinIP",
    "Tr_T_MinIPChi2",
    "Tr_T_PROBNNe",
    "Tr_T_PROBNNghost",
    "Tr_T_PROBNNk",
    "Tr_T_PROBNNmu",
    "Tr_T_PROBNNp",
    "Tr_T_PROBNNpi",
    "Tr_T_P",
    "Tr_T_PT",
    "Tr_T_VeloCharge",
    "Tr_T_SumBDT_ult"
  ],
  "features_B_classifier_baseline_with_Tr_T_Mother_VtxChi2": [
    "Tr_ProbSS",
    "Tr_diff_z",
    "Tr_p_proj",
    "Tr_diff_pt",
    "Tr_diff_p",
    "Tr_cos_diff_phi",
    "Tr_diff_eta",
    "Tr_T_IPCHI2_trMother",
    "Tr_T_IP_trMother",
    "Tr_T_IP_trPUS",
    "Tr_T_MinIP",
    "Tr_T_MinIPChi2",
    "Tr_T_PROBNNe",
    "Tr_T_PROBNNghost",
    "Tr_T_PROBNNk",
    "Tr_T_PROBNNmu",
    "Tr_T_PROBNNp",
    "Tr_T_PROBNNpi",
    "Tr_T_P",
    "Tr_T_PT",
    "Tr_T_VeloCharge",
    "Tr_T_Mother_VtxChi2"
  ],
  "features_B_classifier_baseline_with_Tr_T_ADOCA": [
    "Tr_ProbSS",
    "Tr_diff_z",
    "Tr_p_proj",
    "Tr_diff_pt",
    "Tr_diff_p",
    "Tr_cos_diff_phi",
    "Tr_diff_eta",
    "Tr_T_IPCHI2_trMother",
    "Tr_T_IP_trMother",
    "Tr_T_IP_trPUS",
    "Tr_T_MinIP",
    "Tr_T_MinIPChi2",
    "Tr_T_PROBNNe",
    "Tr_T_PROBNNghost",
    "Tr_T_PROBNNk",
    "Tr_T_PROBNNmu",
    "Tr_T_PROBNNp",
    "Tr_T_PROBNNpi",
    "Tr_T_P",
    "Tr_T_PT",
    "Tr_T_VeloCharge",
    "Tr_T_ADOCA"
  ],
  "features_B_classifier_baseline_with_Tr_T_PIDp": [
    "Tr_ProbSS",
    "Tr_diff_z",
    "Tr_p_proj",
    "Tr_diff_pt",
    "Tr_diff_p",
    "Tr_cos_diff_phi",
    "Tr_diff_eta",
    "Tr_T_IPCHI2_trMother",
    "Tr_T_IP_trMother",
    "Tr_T_IP_trPUS",
    "Tr_T_MinIP",
    "Tr_T_MinIPChi2",
    "Tr_T_PROBNNe",
    "Tr_T_PROBNNghost",
    "Tr_T_PROBNNk",
    "Tr_T_PROBNNmu",
    "Tr_T_PROBNNp",
    "Tr_T_PROBNNpi",
    "Tr_T_P",
    "Tr_T_PT",
    "Tr_T_VeloCharge",
    "Tr_T_PIDp"
  ],
  "features_B_classifier_baseline_with_Tr_T_NbNonIsoTr_MinBDT_ult": [
    "Tr_ProbSS",
    "Tr_diff_z",
    "Tr_p_proj",
    "Tr_diff_pt",
    "Tr_diff_p",
    "Tr_cos_diff_phi",
    "Tr_diff_eta",
    "Tr_T_IPCHI2_trMother",
    "Tr_T_IP_trMother",
    "Tr_T_IP_trPUS",
    "Tr_T_MinIP",
    "Tr_T_MinIPChi2",
    "Tr_T_PROBNNe",
    "Tr_T_PROBNNghost",
    "Tr_T_PROBNNk",
    "Tr_T_PROBNNmu",
    "Tr_T_PROBNNp",
    "Tr_T_PROBNNpi",
    "Tr_T_P",
    "Tr_T_PT",
    "Tr_T_VeloCharge",
    "Tr_T_NbNonIsoTr_MinBDT_ult"
  ],
  "features_B_classifier_baseline_with_Tr_T_PIDK": [
    "Tr_ProbSS",
    "Tr_diff_z",
    "Tr_p_proj",
    "Tr_diff_pt",
    "Tr_diff_p",
    "Tr_cos_diff_phi",
    "Tr_diff_eta",
    "Tr_T_IPCHI2_trMother",
    "Tr_T_IP_trMother",
    "Tr_T_IP_trPUS",
    "Tr_T_MinIP",
    "Tr_T_MinIPChi2",
    "Tr_T_PROBNNe",
    "Tr_T_PROBNNghost",
    "Tr_T_PROBNNk",
    "Tr_T_PROBNNmu",
    "Tr_T_PROBNNp",
    "Tr_T_PROBNNpi",
    "Tr_T_P",
    "Tr_T_PT",
    "Tr_T_VeloCharge",
    "Tr_T_PIDK"
  ],
  "features_B_classifier_baseline_with_Tr_T_yfirst": [
    "Tr_ProbSS",
    "Tr_diff_z",
    "Tr_p_proj",
    "Tr_diff_pt",
    "Tr_diff_p",
    "Tr_cos_diff_phi",
    "Tr_diff_eta",
    "Tr_T_IPCHI2_trMother",
    "Tr_T_IP_trMother",
    "Tr_T_IP_trPUS",
    "Tr_T_MinIP",
    "Tr_T_MinIPChi2",
    "Tr_T_PROBNNe",
    "Tr_T_PROBNNghost",
    "Tr_T_PROBNNk",
    "Tr_T_PROBNNmu",
    "Tr_T_PROBNNp",
    "Tr_T_PROBNNpi",
    "Tr_T_P",
    "Tr_T_PT",
    "Tr_T_VeloCharge",
    "Tr_T_yfirst"
  ],
  "features_B_classifier_baseline_with_Tr_T_PIDe": [
    "Tr_ProbSS",
    "Tr_diff_z",
    "Tr_p_proj",
    "Tr_diff_pt",
    "Tr_diff_p",
    "Tr_cos_diff_phi",
    "Tr_diff_eta",
    "Tr_T_IPCHI2_trMother",
    "Tr_T_IP_trMother",
    "Tr_T_IP_trPUS",
    "Tr_T_MinIP",
    "Tr_T_MinIPChi2",
    "Tr_T_PROBNNe",
    "Tr_T_PROBNNghost",
    "Tr_T_PROBNNk",
    "Tr_T_PROBNNmu",
    "Tr_T_PROBNNp",
    "Tr_T_PROBNNpi",
    "Tr_T_P",
    "Tr_T_PT",
    "Tr_T_VeloCharge",
    "Tr_T_PIDe"
  ],
  "features_B_classifier_baseline_with_Tr_T_MinBDT_ult": [
    "Tr_ProbSS",
    "Tr_diff_z",
    "Tr_p_proj",
    "Tr_diff_pt",
    "Tr_diff_p",
    "Tr_cos_diff_phi",
    "Tr_diff_eta",
    "Tr_T_IPCHI2_trMother",
    "Tr_T_IP_trMother",
    "Tr_T_IP_trPUS",
    "Tr_T_MinIP",
    "Tr_T_MinIPChi2",
    "Tr_T_PROBNNe",
    "Tr_T_PROBNNghost",
    "Tr_T_PROBNNk",
    "Tr_T_PROBNNmu",
    "Tr_T_PROBNNp",
    "Tr_T_PROBNNpi",
    "Tr_T_P",
    "Tr_T_PT",
    "Tr_T_VeloCharge",
    "Tr_T_MinBDT_ult"
  ],
  "features_B_classifier_baseline_with_Tr_T_Phi": [
    "Tr_ProbSS",
    "Tr_diff_z",
    "Tr_p_proj",
    "Tr_diff_pt",
    "Tr_diff_p",
    "Tr_cos_diff_phi",
    "Tr_diff_eta",
    "Tr_T_IPCHI2_trMother",
    "Tr_T_IP_trMother",
    "Tr_T_IP_trPUS",
    "Tr_T_MinIP",
    "Tr_T_MinIPChi2",
    "Tr_T_PROBNNe",
    "Tr_T_PROBNNghost",
    "Tr_T_PROBNNk",
    "Tr_T_PROBNNmu",
    "Tr_T_PROBNNp",
    "Tr_T_PROBNNpi",
    "Tr_T_P",
    "Tr_T_PT",
    "Tr_T_VeloCharge",
    "Tr_T_Phi"
  ],
  "features_B_classifier_baseline_with_Tr_T_Sum_of_trackp": [
    "Tr_ProbSS",
    "Tr_diff_z",
    "Tr_p_proj",
    "Tr_diff_pt",
    "Tr_diff_p",
    "Tr_cos_diff_phi",
    "Tr_diff_eta",
    "Tr_T_IPCHI2_trMother",
    "Tr_T_IP_trMother",
    "Tr_T_IP_trPUS",
    "Tr_T_MinIP",
    "Tr_T_MinIPChi2",
    "Tr_T_PROBNNe",
    "Tr_T_PROBNNghost",
    "Tr_T_PROBNNk",
    "Tr_T_PROBNNmu",
    "Tr_T_PROBNNp",
    "Tr_T_PROBNNpi",
    "Tr_T_P",
    "Tr_T_PT",
    "Tr_T_VeloCharge",
    "Tr_T_Sum_of_trackp"
  ],
  "features_B_classifier_baseline_with_Tr_T_ConIso_p_ult": [
    "Tr_ProbSS",
    "Tr_diff_z",
    "Tr_p_proj",
    "Tr_diff_pt",
    "Tr_diff_p",
    "Tr_cos_diff_phi",
    "Tr_diff_eta",
    "Tr_T_IPCHI2_trMother",
    "Tr_T_IP_trMother",
    "Tr_T_IP_trPUS",
    "Tr_T_MinIP",
    "Tr_T_MinIPChi2",
    "Tr_T_PROBNNe",
    "Tr_T_PROBNNghost",
    "Tr_T_PROBNNk",
    "Tr_T_PROBNNmu",
    "Tr_T_PROBNNp",
    "Tr_T_PROBNNpi",
    "Tr_T_P",
    "Tr_T_PT",
    "Tr_T_VeloCharge",
    "Tr_T_ConIso_p_ult"
  ],
  "features_B_classifier_baseline_with_Tr_T_Sum_of_trackpt": [
    "Tr_ProbSS",
    "Tr_diff_z",
    "Tr_p_proj",
    "Tr_diff_pt",
    "Tr_diff_p",
    "Tr_cos_diff_phi",
    "Tr_diff_eta",
    "Tr_T_IPCHI2_trMother",
    "Tr_T_IP_trMother",
    "Tr_T_IP_trPUS",
    "Tr_T_MinIP",
    "Tr_T_MinIPChi2",
    "Tr_T_PROBNNe",
    "Tr_T_PROBNNghost",
    "Tr_T_PROBNNk",
    "Tr_T_PROBNNmu",
    "Tr_T_PROBNNp",
    "Tr_T_PROBNNpi",
    "Tr_T_P",
    "Tr_T_PT",
    "Tr_T_VeloCharge",
    "Tr_T_Sum_of_trackpt"
  ],
  "features_B_classifier_baseline_with_Tr_T_TRGHOSTPROB": [
    "Tr_ProbSS",
    "Tr_diff_z",
    "Tr_p_proj",
    "Tr_diff_pt",
    "Tr_diff_p",
    "Tr_cos_diff_phi",
    "Tr_diff_eta",
    "Tr_T_IPCHI2_trMother",
    "Tr_T_IP_trMother",
    "Tr_T_IP_trPUS",
    "Tr_T_MinIP",
    "Tr_T_MinIPChi2",
    "Tr_T_PROBNNe",
    "Tr_T_PROBNNghost",
    "Tr_T_PROBNNk",
    "Tr_T_PROBNNmu",
    "Tr_T_PROBNNp",
    "Tr_T_PROBNNpi",
    "Tr_T_P",
    "Tr_T_PT",
    "Tr_T_VeloCharge",
    "Tr_T_TRGHOSTPROB"
  ],
  "features_B_classifier_baseline_with_Tr_T_y": [
    "Tr_ProbSS",
    "Tr_diff_z",
    "Tr_p_proj",
    "Tr_diff_pt",
    "Tr_diff_p",
    "Tr_cos_diff_phi",
    "Tr_diff_eta",
    "Tr_T_IPCHI2_trMother",
    "Tr_T_IP_trMother",
    "Tr_T_IP_trPUS",
    "Tr_T_MinIP",
    "Tr_T_MinIPChi2",
    "Tr_T_PROBNNe",
    "Tr_T_PROBNNghost",
    "Tr_T_PROBNNk",
    "Tr_T_PROBNNmu",
    "Tr_T_PROBNNp",
    "Tr_T_PROBNNpi",
    "Tr_T_P",
    "Tr_T_PT",
    "Tr_T_VeloCharge",
    "Tr_T_y"
  ],
  "features_B_classifier_baseline_with_Tr_T_BPVIPCHI2": [
    "Tr_ProbSS",
    "Tr_diff_z",
    "Tr_p_proj",
    "Tr_diff_pt",
    "Tr_diff_p",
    "Tr_cos_diff_phi",
    "Tr_diff_eta",
    "Tr_T_IPCHI2_trMother",
    "Tr_T_IP_trMother",
    "Tr_T_IP_trPUS",
    "Tr_T_MinIP",
    "Tr_T_MinIPChi2",
    "Tr_T_PROBNNe",
    "Tr_T_PROBNNghost",
    "Tr_T_PROBNNk",
    "Tr_T_PROBNNmu",
    "Tr_T_PROBNNp",
    "Tr_T_PROBNNpi",
    "Tr_T_P",
    "Tr_T_PT",
    "Tr_T_VeloCharge",
    "Tr_T_BPVIPCHI2"
  ],
  "features_B_classifier_baseline_with_Tr_T_NbTrNonIso_sigtr": [
    "Tr_ProbSS",
    "Tr_diff_z",
    "Tr_p_proj",
    "Tr_diff_pt",
    "Tr_diff_p",
    "Tr_cos_diff_phi",
    "Tr_diff_eta",
    "Tr_T_IPCHI2_trMother",
    "Tr_T_IP_trMother",
    "Tr_T_IP_trPUS",
    "Tr_T_MinIP",
    "Tr_T_MinIPChi2",
    "Tr_T_PROBNNe",
    "Tr_T_PROBNNghost",
    "Tr_T_PROBNNk",
    "Tr_T_PROBNNmu",
    "Tr_T_PROBNNp",
    "Tr_T_PROBNNpi",
    "Tr_T_P",
    "Tr_T_PT",
    "Tr_T_VeloCharge",
    "Tr_T_NbTrNonIso_sigtr"
  ],
  "features_B_classifier_baseline_with_Tr_T_BPVIP": [
    "Tr_ProbSS",
    "Tr_diff_z",
    "Tr_p_proj",
    "Tr_diff_pt",
    "Tr_diff_p",
    "Tr_cos_diff_phi",
    "Tr_diff_eta",
    "Tr_T_IPCHI2_trMother",
    "Tr_T_IP_trMother",
    "Tr_T_IP_trPUS",
    "Tr_T_MinIP",
    "Tr_T_MinIPChi2",
    "Tr_T_PROBNNe",
    "Tr_T_PROBNNghost",
    "Tr_T_PROBNNk",
    "Tr_T_PROBNNmu",
    "Tr_T_PROBNNp",
    "Tr_T_PROBNNpi",
    "Tr_T_P",
    "Tr_T_PT",
    "Tr_T_VeloCharge",
    "Tr_T_BPVIP"
  ],
  "features_B_classifier_baseline_with_Tr_T_xfirst": [
    "Tr_ProbSS",
    "Tr_diff_z",
    "Tr_p_proj",
    "Tr_diff_pt",
    "Tr_diff_p",
    "Tr_cos_diff_phi",
    "Tr_diff_eta",
    "Tr_T_IPCHI2_trMother",
    "Tr_T_IP_trMother",
    "Tr_T_IP_trPUS",
    "Tr_T_MinIP",
    "Tr_T_MinIPChi2",
    "Tr_T_PROBNNe",
    "Tr_T_PROBNNghost",
    "Tr_T_PROBNNk",
    "Tr_T_PROBNNmu",
    "Tr_T_PROBNNp",
    "Tr_T_PROBNNpi",
    "Tr_T_P",
    "Tr_T_PT",
    "Tr_T_VeloCharge",
    "Tr_T_xfirst"
  ],
  "features_B_classifier_all": [
    "Tr_ProbSS",
    "Tr_diff_z",
    "Tr_p_proj",
    "Tr_diff_pt",
    "Tr_diff_p",
    "Tr_cos_diff_phi",
    "Tr_diff_eta",
    "Tr_T_AALLSAMEBPV",
    "Tr_T_ACHI2DOCA",
    "Tr_T_ADOCA",
    "Tr_T_BPVIP",
    "Tr_T_BPVIPCHI2",
    "Tr_T_Best_PAIR_M_fromiso",
    "Tr_T_Charge",
    "Tr_T_ConIso_p_ult",
    "Tr_T_ConIso_pt_ult",
    "Tr_T_IPCHI2_trMother",
    "Tr_T_IP_trMother",
    "Tr_T_IP_trPUS",
    "Tr_T_ISMUON",
    "Tr_T_MinBDT_sigtr",
    "Tr_T_MinBDT_ult",
    "Tr_T_MinIP",
    "Tr_T_MinIPChi2",
    "Tr_T_Mother_VtxChi2",
    "Tr_T_NbNonIsoTr_MinBDT_ult",
    "Tr_T_NbNonIsoTr_ult",
    "Tr_T_NbTrNonIso_sigtr",
    "Tr_T_Ntr_incone",
    "Tr_T_PIDK",
    "Tr_T_PIDe",
    "Tr_T_PIDmu",
    "Tr_T_PIDp",
    "Tr_T_PROBNNe",
    "Tr_T_PROBNNghost",
    "Tr_T_PROBNNk",
    "Tr_T_PROBNNmu",
    "Tr_T_PROBNNp",
    "Tr_T_PROBNNpi",
    "Tr_T_P",
    "Tr_T_PT",
    "Tr_T_Phi",
    "Tr_T_SumBDT_sigtr",
    "Tr_T_SumBDT_ult",
    "Tr_T_SumMinBDT_ult",
    "Tr_T_Sum_of_trackp",
    "Tr_T_Sum_of_trackpt",
    "Tr_T_TRCHI2DOF",
    "Tr_T_TRFITTCHI2",
    "Tr_T_TrFITTCHI2NDOF",
    "Tr_T_TRFITVELOCHI2NDOF",
    "Tr_T_TRGHOSTPROB",
    "Tr_T_TRPCHI2",
    "Tr_T_VeloCharge",
    "Tr_T_x",
    "Tr_T_xfirst",
    "Tr_T_y",
    "Tr_T_yfirst"
  ]
}